xia_cache_http/__init__.py
xia_cache_http/cache.cpython-310-x86_64-linux-gnu.so
xia_cache_http-0.0.2.dist-info/LICENSE
xia_cache_http-0.0.2.dist-info/METADATA
xia_cache_http-0.0.2.dist-info/WHEEL
xia_cache_http-0.0.2.dist-info/top_level.txt
xia_cache_http-0.0.2.dist-info/RECORD
