Metadata-Version: 2.1
Name: xia-cache-http
Version: 0.0.2
Summary: Cache Engine with Firestore as backend
Home-page: https://git.top-infra.com/
Author: Xia CHEN
Author-email: admin@x-i-a.com
Requires-Python: >=3.7
License-File: LICENSE
Requires-Dist: requests
Requires-Dist: xia-cache
